sca2d/__init__.py
sca2d/__main__.py
sca2d/definitions.py
sca2d/docs.py
sca2d/generate.py
sca2d/messages.py
sca2d/outerscope.py
sca2d/patterns.py
sca2d/sca2d.py
sca2d/scadclasses.py
sca2d/scope.py
sca2d/utilities.py
sca2d/lark/scad.lark
sca2d/templates/apidocs_page.html.jinja
sca2d/templates/default.html.jinja
sca2d/templates/footer.html.jinja
sca2d/templates/head.html.jinja
sca2d/templates/index.html.jinja
sca2d/templates/page_style.html.jinja
sca2d/templates/sidebar.html.jinja
sca2d-0.3.1.dist-info/METADATA
sca2d-0.3.1.dist-info/WHEEL
sca2d-0.3.1.dist-info/entry_points.txt
sca2d-0.3.1.dist-info/licenses/LICENSE
sca2d-0.3.1.dist-info/RECORD
