Metadata-Version: 2.4
Name: sca2d
Version: 0.3.1
Summary: A static code analyser for OpenSCAD.
Project-URL: Homepage, https://gitlab.com/bath_open_instrumentation_group/sca2d
Project-URL: Bug Tracker, https://gitlab.com/bath_open_instrumentation_group/sca2d/issues
Project-URL: Source Code, https://gitlab.com/bath_open_instrumentation_group/sca2d
Author-email: Julian Stirling <julian@julianstirling.co.uk>
License-File: LICENSE
Keywords: Linting,OpenSCAD
Classifier: License :: OSI Approved :: GNU General Public License v3 (GPLv3)
Classifier: Operating System :: OS Independent
Classifier: Programming Language :: Python :: 3
Requires-Python: >=3.9
Requires-Dist: colorama
Requires-Dist: jinja2~=3.1
Requires-Dist: lark-parser
Requires-Dist: markdown~=3.8
Requires-Dist: pygments~=2.19
Provides-Extra: dev
Requires-Dist: build; extra == 'dev'
Requires-Dist: codespell; extra == 'dev'
Requires-Dist: coverage; extra == 'dev'
Requires-Dist: ruff; extra == 'dev'
Requires-Dist: twine; extra == 'dev'
